timehash/__init__.py
timehash-1.2.dist-info/LICENSE
timehash-1.2.dist-info/METADATA
timehash-1.2.dist-info/WHEEL
timehash-1.2.dist-info/top_level.txt
timehash-1.2.dist-info/RECORD
