Metadata-Version: 2.1
Name: timehash
Version: 1.2
Summary: Module to encode and decode timestamps to/from TimeHashes
Home-page: https://github.com/abeusher/timehash
Author: Abe Usher
Author-email: abe.usher@gmail.com
License: UNKNOWN
Download-URL: https://github.com/abeusher/timehash/tarball/1.2
Keywords: timehash,datetime,time
Platform: UNKNOWN
